geoapps/__init__.py
geoapps/base/__init__.py
geoapps/base/application.py
geoapps/base/dash_application.py
geoapps/base/layout.py
geoapps/base/plot.py
geoapps/base/selection.py
geoapps/block_model_creation/application.py
geoapps/block_model_creation/constants.py
geoapps/block_model_creation/driver.py
geoapps/block_model_creation/layout.py
geoapps/block_model_creation/notebook.ipynb
geoapps/block_model_creation/params.py
geoapps/calculator/__init__.py
geoapps/calculator/application.py
geoapps/calculator/notebook.ipynb
geoapps/clustering/__init__.py
geoapps/clustering/application.py
geoapps/clustering/constants.py
geoapps/clustering/driver.py
geoapps/clustering/layout.py
geoapps/clustering/notebook.ipynb
geoapps/clustering/params.py
geoapps/clustering/plot_data.py
geoapps/contours/__init__.py
geoapps/contours/application.py
geoapps/contours/constants.py
geoapps/contours/driver.py
geoapps/contours/notebook.ipynb
geoapps/contours/params.py
geoapps/coordinate_transformation/__init__.py
geoapps/coordinate_transformation/application.py
geoapps/coordinate_transformation/notebook.ipynb
geoapps/coordinate_transformation/utils.py
geoapps/driver_base/__init__.py
geoapps/driver_base/driver.py
geoapps/driver_base/params.py
geoapps/driver_base/utils.py
geoapps/edge_detection/__init__.py
geoapps/edge_detection/application.py
geoapps/edge_detection/constants.py
geoapps/edge_detection/driver.py
geoapps/edge_detection/notebook.ipynb
geoapps/edge_detection/params.py
geoapps/export/__init__.py
geoapps/export/application.py
geoapps/export/notebook.ipynb
geoapps/export/utils.py
geoapps/images/blankworkspace.png
geoapps/images/block_model_and_object.png
geoapps/images/block_model_app.png
geoapps/images/block_model_thumbnail.png
geoapps/images/calculator_app.png
geoapps/images/calculator_thumbnail.png
geoapps/images/cdi_surface_app.png
geoapps/images/cluster_thumbnail.png
geoapps/images/clustering_app.gif
geoapps/images/Contouring_app.png
geoapps/images/contours_thumbnail.png
geoapps-0.11.1.dist-info/entry_points.txt
geoapps-0.11.1.dist-info/LICENSE
geoapps-0.11.1.dist-info/METADATA
geoapps-0.11.1.dist-info/WHEEL
geoapps-0.11.1.dist-info/RECORD
