Metadata-Version: 2.1
Name: geoapps
Version: 0.11.1
Summary: Open-sourced Applications in Geoscience
Home-page: https://mirageoscience.com
License: MIT
Keywords: geology,geophysics,earth sciences
Author: Mira Geoscience
Author-email: dominiquef@mirageoscience.com
Requires-Python: >=3.9,<3.11
Classifier: Development Status :: 4 - Beta
Classifier: Intended Audience :: Science/Research
Classifier: License :: OSI Approved :: MIT License
Classifier: Natural Language :: English
Classifier: Operating System :: MacOS
Classifier: Operating System :: Microsoft :: Windows
Classifier: Operating System :: POSIX
Classifier: Operating System :: Unix
Classifier: Programming Language :: Python
Classifier: Programming Language :: Python :: 3
Classifier: Programming Language :: Python :: 3.9
Classifier: Programming Language :: Python :: 3.10
Classifier: Topic :: Scientific/Engineering
Classifier: Topic :: Scientific/Engineering :: Mathematics
Classifier: Topic :: Scientific/Engineering :: Physics
Provides-Extra: apps
Provides-Extra: core
Requires-Dist: Pillow (>=10.0.1,<11.0.0)
Requires-Dist: dash-daq (>=0.5.0,<0.6.0) ; extra == "apps"
Requires-Dist: dask[distributed] (==2022.10.*) ; extra == "core"
Requires-Dist: discretize (>=0.10.0,<0.11.0) ; extra == "core"
Requires-Dist: distributed (==2022.10.*) ; extra == "core"
Requires-Dist: empymod (>=2.2.1,<2.3.0) ; extra == "core"
Requires-Dist: fiona (>=1.9.2,<1.10.0) ; extra == "core"
Requires-Dist: fsspec (==2022.*) ; extra == "core"
Requires-Dist: gdal (>=3.6.3,<3.7.0) ; extra == "core"
Requires-Dist: geoana (>=0.4.0,<0.5.0) ; extra == "core"
Requires-Dist: geoh5py (>=0.8.0,<0.9.0)
Requires-Dist: h5py (>=3.2.1,<4.0.0)
Requires-Dist: ipyfilechooser (>=0.6.0,<0.7.0) ; extra == "apps"
Requires-Dist: ipywidgets (>=7.6.5,<8.0.0) ; extra == "apps"
Requires-Dist: las-geoh5 (>=0.1.0,<0.2.0)
Requires-Dist: matplotlib (>=3.7.1,<3.8.0) ; extra == "core"
Requires-Dist: mira-omf (>=3.1.0,<3.2.0)
Requires-Dist: mira-simpeg (>=0.19.0.dev7,<0.20.0) ; extra == "core"
Requires-Dist: mkl (==2022.*) ; extra == "core"
Requires-Dist: numpy (>=1.23.5,<1.24.0)
Requires-Dist: pandas (>=1.5.3,<1.6.0) ; extra == "core"
Requires-Dist: param-sweeps (>=0.1.6,<0.2.0)
Requires-Dist: plotly (>=5.13.1,<5.14.0) ; extra == "apps"
Requires-Dist: properties (>=0.6.0,<0.7.0)
Requires-Dist: pydiso (>=0.0.3,<0.1.0) ; extra == "core"
Requires-Dist: pymatsolver (>=0.2.0,<0.3.0) ; extra == "core"
Requires-Dist: pypng (>=0.20220715,<0.20220716)
Requires-Dist: pyqtwebengine (>=5.15,<5.16) ; extra == "apps"
Requires-Dist: pyside2 (>=5.15,<5.16) ; extra == "apps"
Requires-Dist: scikit-image (>=0.19.2,<0.20.0) ; extra == "core"
Requires-Dist: scikit-learn (>=1.2.2,<1.3.0) ; extra == "core"
Requires-Dist: scipy (>=1.10.1,<1.11.0)
Requires-Dist: semver (>=3.0.0,<3.1.0)
Requires-Dist: simpeg-archive (>=0.11.0.dev6,<0.12.0) ; extra == "core"
Requires-Dist: six (>=1.16,<2.0)
Requires-Dist: tqdm (>=4.64.0,<5.0.0) ; extra == "core"
Requires-Dist: vectormath (>=0.2.0,<0.3.0)
Requires-Dist: zarr (>=2.14.2,<2.15.0) ; extra == "core"
Project-URL: Documentation, https://geoapps.readthedocs.io/en/latest/
Project-URL: Repository, https://github.com/MiraGeoscience/geoapps
